[
    {
      "serviceProvider": {
        "name": "HeavyMach Ltd",
        "image": "https://i.ibb.co/mXD5MNf/facebook.png",
        "location": "DHAKA"
      },
      "service": {
        "image": "https://i.ibb.co/BLVwZzZ/icons8-whatsapp-logo-94.png",
        "name": "Excavator Rental",
        "description": "Rent excavators for construction projects. Well-maintained equipment available.",
        "providerImage": "https://i.ibb.co/mXD5MNf/facebook.png",
        "providerName": "HeavyMach Ltd",
        "price": {
          "min": 5000,
          "max": 10000,
          "currency": "BDT"
        }
      }
    },
    {
      "serviceProvider": {
        "name": "CargoMover",
        "image": "https://i.ibb.co/TvvzXfq/google.png",
        "location": "COMILLA"
      },
      "service": {
        "image": "https://i.ibb.co/BLVwZzZ/icons8-whatsapp-logo-94.png",
        "name": "Truck Rental",
        "description": "Rent heavy-duty trucks for local and interstate hauling of large goods.",
        "providerImage": "https://i.ibb.co/TvvzXfq/google.png",
        "providerName": "CargoMover",
        "price": {
          "min": 10000,
          "max": 20000,
          "currency": "BDT"
        }
      }
    },
    {
      "serviceProvider": {
        "name": "Mega Earthworks",
        "image": "https://i.ibb.co/T1XRmbX/linkedin.png",
        "location": "MUNSHIGANJ"
      },
      "service": {
        "image": "https://i.ibb.co/BLVwZzZ/icons8-whatsapp-logo-94.png",
        "name": "Bulldozer Rental",
        "description": "Bulldozers available for construction, earth-moving, and site clearing work.",
        "providerImage": "https://i.ibb.co/T1XRmbX/linkedin.png",
        "providerName": "Mega Earthworks",
        "price": {
          "min": 12000,
          "max": 15000,
          "currency": "BDT"
        }
      }
    },
    {
      "serviceProvider": {
        "name": "FarmTech Ltd",
        "image": "https://i.ibb.co/MhsV6wz/microsoft.png",
        "location": "JESSORE"
      },
      "service": {
        "image": "https://i.ibb.co/BLVwZzZ/icons8-whatsapp-logo-94.png",
        "name": "Tractor Rental",
        "description": "Rent tractors for agricultural tasks like plowing and seeding. Flexible rentals.",
        "providerImage": "https://i.ibb.co/MhsV6wz/microsoft.png",
        "providerName": "FarmTech Ltd",
        "price": {
          "min": 7000,
          "max": 12000,
          "currency": "BDT"
        }
      }
    },
    {
      "serviceProvider": {
        "name": "TransportKing",
        "image": "https://i.ibb.co/r5WyzKm/icons8-apple-logo-100.png",
        "location": "NARAYANGANJ"
      },
      "service": {
        "image": "https://i.ibb.co/BLVwZzZ/icons8-whatsapp-logo-94.png",
        "name": "Lowbed Trailer Rental",
        "description": "Rent lowbed trailers for transporting heavy machinery and equipment securely.",
        "providerImage": "https://i.ibb.co/r5WyzKm/icons8-apple-logo-100.png",
        "providerName": "TransportKing",
        "price": {
          "min": 15000,
          "max": 25000,
          "currency": "BDT"
        }
      }
    },
    {
      "serviceProvider": {
        "name": "CityWaste Management",
        "image": "https://i.ibb.co/pvG4Ph9/icons8-amazon-logo-96.png",
        "location": "RAJSHAHI"
      },
      "service": {
        "image": "https://i.ibb.co/BLVwZzZ/icons8-whatsapp-logo-94.png",
        "name": "Dump Truck Rental",
        "description": "Rent dump trucks for construction debris removal and large material transport.",
        "providerImage": "https://i.ibb.co/pvG4Ph9/icons8-amazon-logo-96.png",
        "providerName": "CityWaste Management",
        "price": {
          "min": 8000,
          "max": 15000,
          "currency": "BDT"
        }
      }
    },
    {
      "serviceProvider": {
        "name": "BuildPro Ltd",
        "image": "https://i.ibb.co/ThtyXpz/netflix.png",
        "location": "BARISAL"
      },
      "service": {
        "image": "https://i.ibb.co/BLVwZzZ/icons8-whatsapp-logo-94.png",
        "name": "Concrete Mixer Rental",
        "description": "Rent concrete mixers for efficient mixing during construction projects.",
        "providerImage": "https://i.ibb.co/ThtyXpz/netflix.png",
        "providerName": "BuildPro Ltd",
        "price": {
          "min": 10000,
          "max": 20000,
          "currency": "BDT"
        }
      }
    },
    {
      "serviceProvider": {
        "name": "SkyLifter",
        "image": "https://i.ibb.co/Kw72gGC/icons8-youtube-logo-100.png",
        "location": "KHULNA"
      },
      "service": {
        "image": "https://i.ibb.co/BLVwZzZ/icons8-whatsapp-logo-94.png",
        "name": "Cranes Rental",
        "description": "Rent cranes for lifting heavy loads and performing construction tasks.",
        "providerImage": "https://i.ibb.co/Kw72gGC/icons8-youtube-logo-100.png",
        "providerName": "SkyLifter",
        "price": {
          "min": 20000,
          "max": 40000,
          "currency": "BDT"
        }
      }
    },
    {
      "serviceProvider": {
        "name": "LiftMaster",
        "image": "https://i.ibb.co/T1XRmbX/linkedin.png",
        "location": "SYLHET"
      },
      "service": {
        "image": "https://i.ibb.co/BLVwZzZ/icons8-whatsapp-logo-94.png",
        "name": "Forklift Rental",
        "description": "Rent forklifts for material handling in warehouses and construction sites.",
        "providerImage": "https://i.ibb.co/T1XRmbX/linkedin.png",
        "providerName": "LiftMaster",
        "price": {
          "min": 6000,
          "max": 12000,
          "currency": "BDT"
        }
      }
    },
    {
      "serviceProvider": {
        "name": "PavementPro",
        "image": "https://i.ibb.co/r5WyzKm/icons8-apple-logo-100.png",
        "location": "FENI"
      },
      "service": {
        "image": "https://i.ibb.co/BLVwZzZ/icons8-whatsapp-logo-94.png",
        "name": "Road Roller Rental",
        "description": "Rent road rollers for asphalt compaction and road construction projects.",
        "providerImage": "https://i.ibb.co/r5WyzKm/icons8-apple-logo-100.png",
        "providerName": "PavementPro",
        "price": {
          "min": 13000,
          "max": 25000,
          "currency": "BDT"
        }
      }
    },
    {
      "serviceProvider": {
        "name": "Mega Movers",
        "image": "https://i.ibb.co/mXD5MNf/facebook.png",
        "location": "DHAKA"
      },
      "service": {
        "image": "https://i.ibb.co/BLVwZzZ/icons8-whatsapp-logo-94.png",
        "name": "Heavy Duty Crane Rental",
        "description": "Rent heavy-duty cranes for lifting and moving large, heavy objects.",
        "providerImage": "https://i.ibb.co/mXD5MNf/facebook.png",
        "providerName": "Mega Movers",
        "price": {
          "min": 15000,
          "max": 30000,
          "currency": "BDT"
        }
      }
    },
    {
      "serviceProvider": {
        "name": "EarthMakers",
        "image": "https://i.ibb.co/TvvzXfq/google.png",
        "location": "COMILLA"
      },
      "service": {
        "image": "https://i.ibb.co/BLVwZzZ/icons8-whatsapp-logo-94.png",
        "name": "Excavator Loader Rental",
        "description": "Excavators and loaders for earthworks, site clearing, and demolition tasks.",
        "providerImage": "https://i.ibb.co/TvvzXfq/google.png",
        "providerName": "EarthMakers",
        "price": {
          "min": 12000,
          "max": 22000,
          "currency": "BDT"
        }
      }
    },
    {
      "serviceProvider": {
        "name": "ConstructionPro",
        "image": "https://i.ibb.co/T1XRmbX/linkedin.png",
        "location": "MUNSHIGANJ"
      },
      "service": {
        "image": "https://i.ibb.co/BLVwZzZ/icons8-whatsapp-logo-94.png",
        "name": "Lifting Equipment Rental",
        "description": "Rent equipment for lifting and handling heavy loads efficiently.",
        "providerImage": "https://i.ibb.co/T1XRmbX/linkedin.png",
        "providerName": "ConstructionPro",
        "price": {
          "min": 18000,
          "max": 35000,
          "currency": "BDT"
        }
      }
    },
    {
      "serviceProvider": {
        "name": "LiftPro",
        "image": "https://i.ibb.co/pvG4Ph9/icons8-amazon-logo-96.png",
        "location": "RAJSHAHI"
      },
      "service": {
        "image": "https://i.ibb.co/BLVwZzZ/icons8-whatsapp-logo-94.png",
        "name": "Truck Mounted Crane Rental",
        "description": "Rent truck-mounted cranes for material lifting at construction sites.",
        "providerImage": "https://i.ibb.co/pvG4Ph9/icons8-amazon-logo-96.png",
        "providerName": "LiftPro",
        "price": {
          "min": 25000,
          "max": 45000,
          "currency": "BDT"
        }
      }
    },
    {
      "serviceProvider": {
        "name": "MegaBuilders",
        "image": "https://i.ibb.co/MhsV6wz/microsoft.png",
        "location": "SYLHET"
      },
      "service": {
        "image": "https://i.ibb.co/BLVwZzZ/icons8-whatsapp-logo-94.png",
        "name": "Dozer Blade Rental",
        "description": "Rent bulldozer blades for earth-moving and land grading purposes.",
        "providerImage": "https://i.ibb.co/MhsV6wz/microsoft.png",
        "providerName": "MegaBuilders",
        "price": {
          "min": 8000,
          "max": 12000,
          "currency": "BDT"
        }
      }
    },
    {
      "serviceProvider": {
        "name": "SkyTower",
        "image": "https://i.ibb.co/r5WyzKm/icons8-apple-logo-100.png",
        "location": "KHULNA"
      },
      "service": {
        "image": "https://i.ibb.co/BLVwZzZ/icons8-whatsapp-logo-94.png",
        "name": "Elevated Work Platform Rental",
        "description": "Rent elevated work platforms for high-rise construction and maintenance tasks.",
        "providerImage": "https://i.ibb.co/r5WyzKm/icons8-apple-logo-100.png",
        "providerName": "SkyTower",
        "price": {
          "min": 30000,
          "max": 50000,
          "currency": "BDT"
        }
      }
    },
    {
      "serviceProvider": {
        "name": "GreenEnergy Builders",
        "image": "https://i.ibb.co/ThtyXpz/netflix.png",
        "location": "BARISAL"
      },
      "service": {
        "image": "https://i.ibb.co/BLVwZzZ/icons8-whatsapp-logo-94.png",
        "name": "Solar Panel Truck Rental",
        "description": "Rent specialized trucks equipped for solar panel transportation.",
        "providerImage": "https://i.ibb.co/ThtyXpz/netflix.png",
        "providerName": "GreenEnergy Builders",
        "price": {
          "min": 15000,
          "max": 25000,
          "currency": "BDT"
        }
      }
    }
  ]
  